darfix_batch/__init__.py
darfix_batch/__main__.py
darfix_batch/main.py
darfix_batch/common/__init__.py
darfix_batch/common/gui/__init__.py
darfix_batch/common/gui/jobs_list_widget.py
darfix_batch/common/gui/workflow_executor.py
darfix_batch/core/darfix_metadata.py
darfix_batch/gui/darfix_jobs_list_widget.py
darfix_batch/gui/file_browser.py
darfix_batch/gui/main_window.py
darfix_batch/gui/output_group.py
darfix_batch/gui/scan_tree.py
darfix_batch/gui/workspace_browser.py
darfix_batch/tests/__init__.py
darfix_batch/tests/test_main_window.py
darfix_batch/tests/utils.py
darfix_batch/tests/resources/__init__.py
darfix_batch/tests/resources/grainplot.ows
darfix_batch-0.1.2.dist-info/licenses/LICENSE
darfix_batch-0.1.2.dist-info/METADATA
darfix_batch-0.1.2.dist-info/WHEEL
darfix_batch-0.1.2.dist-info/entry_points.txt
darfix_batch-0.1.2.dist-info/top_level.txt
darfix_batch-0.1.2.dist-info/RECORD
