Metadata-Version: 2.4
Name: darfix_batch
Version: 0.1.2
Summary: Darfix GUI for batch processing
Author-email: ESRF <dau-pydev@esrf.fr>
License: The MIT license follows:
Project-URL: Homepage, https://gitlab.esrf.fr/XRD/darfix_batch
Project-URL: Documentation, https://darfix_batch.readthedocs.io/
Project-URL: Repository, https://gitlab.esrf.fr/XRD/darfix_batch
Project-URL: Issues, https://gitlab.esrf.fr/XRD/darfix_batch/issues/
Project-URL: Changelog, https://gitlab.esrf.fr/XRD/darfix_batch/-/blob/main/CHANGELOG.md
Classifier: Intended Audience :: Science/Research
Classifier: License :: OSI Approved :: MIT License
Classifier: Programming Language :: Python :: 3
Requires-Python: >=3.8
License-File: LICENSE
Requires-Dist: darfix[full]
Requires-Dist: ewoksjob
Requires-Dist: qtawesome
Provides-Extra: test
Requires-Dist: pytest>=7; extra == "test"
Requires-Dist: pytest-qt; extra == "test"
Provides-Extra: doc
Requires-Dist: ewokssphinx>=1.0.0; extra == "doc"
Requires-Dist: sphinx>=4.5; extra == "doc"
Requires-Dist: sphinx-autodoc-typehints>=1.16; extra == "doc"
Requires-Dist: pydata_sphinx_theme; extra == "doc"
Requires-Dist: sphinxcontrib-autoprogram; extra == "doc"
Requires-Dist: sphinx-argparse; extra == "doc"
Requires-Dist: sphinx-copybutton; extra == "doc"
Dynamic: license-file
